worldenergydata/__init__.py
worldenergydata/__main__.py
worldenergydata/engine.py
worldenergydata/base_configs/modules/bsee/bsee.yml
worldenergydata/base_configs/modules/bsee/production_data_by_lease.yml
worldenergydata/base_configs/modules/bsee/retrieve_data_from_files.yml
worldenergydata/base_configs/modules/dwnld_from_zipurl/dwnld_from_zipurl.yml
worldenergydata/base_configs/modules/zip_utils/zip_utils.yml
worldenergydata/common/bsee/retrieve_data_templates.py
worldenergydata/common/legacy/bsee_data_manager.py
worldenergydata/common/legacy/bsee_data_refresh.py
worldenergydata/common/legacy/data.py
worldenergydata/common/legacy/data_models_components.py
worldenergydata/common/legacy/ong_fd_components.py
worldenergydata/common/legacy/visualization.py
worldenergydata/common/legacy/wellpath3D.py
worldenergydata/common/legacy/bsee/retrieve_data_templates.py
worldenergydata/common/legacy/legacy/bsee_data_manager.py
worldenergydata/common/legacy/legacy/bsee_data_refresh.py
worldenergydata/common/legacy/legacy/data.py
worldenergydata/modules/bsee/bsee.py
worldenergydata/modules/bsee/analysis/bsee_analysis.py
worldenergydata/modules/bsee/analysis/prepare_data_for_analysis.py
worldenergydata/modules/bsee/analysis/production_api10.py
worldenergydata/modules/bsee/analysis/production_api12.py
worldenergydata/modules/bsee/analysis/temp.py
worldenergydata/modules/bsee/analysis/well_api10.py
worldenergydata/modules/bsee/analysis/well_api12.py
worldenergydata/modules/bsee/analysis/well_rig_days.py
worldenergydata/modules/bsee/analysis/legacy/prepare_data_for_analysis.py
worldenergydata/modules/bsee/data/apm_data.py
worldenergydata/modules/bsee/data/block.py
worldenergydata/modules/bsee/data/block_data.py
worldenergydata/modules/bsee/data/bsee_data.py
worldenergydata/modules/bsee/data/data_from_production_files.py
worldenergydata/modules/bsee/data/data_refresh.py
worldenergydata/modules/bsee/data/get_zip_well_production_data.py
worldenergydata/modules/bsee/data/production.py
worldenergydata-0.0.1.dist-info/licenses/LICENSE
worldenergydata-0.0.1.dist-info/METADATA
worldenergydata-0.0.1.dist-info/WHEEL
worldenergydata-0.0.1.dist-info/entry_points.txt
worldenergydata-0.0.1.dist-info/top_level.txt
worldenergydata-0.0.1.dist-info/RECORD
