Metadata-Version: 2.4
Name: worldenergydata
Version: 0.0.1
Summary: World Energy Data from Public Sources
Author-email: Vamsee Achanta <vamsee.achanta@aceengineer.com>
License: MIT License
Project-URL: repository, https://github.com/vamseeachanta/worldenergydata
Project-URL: documentation, https://github.com/vamseeachanta/worldenergydata/blob/main/README.md
Keywords: package,library,module
Classifier: License :: OSI Approved :: MIT License
Classifier: Programming Language :: Python
Classifier: Programming Language :: Python :: 3
Requires-Python: >=3.7
License-File: LICENSE
Requires-Dist: pyyaml
Requires-Dist: tomli; python_version < "3.11"
Provides-Extra: build
Requires-Dist: build; extra == "build"
Requires-Dist: twine; extra == "build"
Provides-Extra: dev
Requires-Dist: black; extra == "dev"
Requires-Dist: bumpver; extra == "dev"
Requires-Dist: isort; extra == "dev"
Requires-Dist: pytest; extra == "dev"
Dynamic: license-file
